MANIFEST.in
README.md
setup.py
vitalstyles/__init__.py
vitalstyles/cli.py
vitalstyles/commentparser.py
vitalstyles/guide.py
vitalstyles/markdownparser.py
vitalstyles/settings.py
vitalstyles.egg-info/PKG-INFO
vitalstyles.egg-info/SOURCES.txt
vitalstyles.egg-info/dependency_links.txt
vitalstyles.egg-info/entry_points.txt
vitalstyles.egg-info/not-zip-safe
vitalstyles.egg-info/requires.txt
vitalstyles.egg-info/top_level.txt
vitalstyles/stock_assets/stock/1000x650gray.jpg
vitalstyles/stock_assets/stock/1100x2000sky.jpg
vitalstyles/stock_assets/stock/120x75green.jpg
vitalstyles/stock_assets/stock/120x90dark.jpg
vitalstyles/stock_assets/stock/120x90light.jpg
vitalstyles/stock_assets/stock/2000x1100sky.jpg
vitalstyles/stock_assets/stock/2000x550sky.jpg
vitalstyles/stock_assets/stock/300x188green.jpg
vitalstyles/stock_assets/stock/300x225dark.jpg
vitalstyles/stock_assets/stock/300x225light.jpg
vitalstyles/stock_assets/stock/800x500green.jpg
vitalstyles/stock_assets/stock/800x600dark.jpg
vitalstyles/stock_assets/stock/800x600light.jpg
vitalstyles/styles/styles.css
vitalstyles/templates/example.html
vitalstyles/templates/index.html
vitalstyles/templates/preview-default.html
vitalstyles/templates/preview-fullwidth.html
vitalstyles/templates/preview-isolated.html
vitalstyles/templates/preview-standalone.html