Metadata-Version: 1.1
Name: vitalstyles
Version: 1.1.3
Summary: Generate CSS/SASS/LESS documentation with previews using Markdown in comments.
Home-page: https://github.com/appressoas/vitalstyles
Author: Espen Angell Kristiansen
Author-email: post@espenak.net
License: BSD
Platform: UNKNOWN
Classifier: Intended Audience :: Developers
Classifier: License :: OSI Approved
Classifier: Programming Language :: Python
